unblockedGPT/GPTHeroAuth.py
unblockedGPT/__init__.py
unblockedGPT/__main__.py
unblockedGPT/app.py
unblockedGPT/auth.py
unblockedGPT/detection.py
unblockedGPT/projectDataTypes.py
unblockedGPT/rephrase.py
unblockedGPT/saveKeysCmd.py
unblockedGPT/saveResponse.py
unblockedGPT/timeToType.py
unblockedGPT/type.py
unblockedGPT/typeGPT.py
unblockedGPT/typeresponse.py
unblockedGPT-1.4.1.dist-info/LICENSE
unblockedGPT-1.4.1.dist-info/METADATA
unblockedGPT-1.4.1.dist-info/WHEEL
unblockedGPT-1.4.1.dist-info/entry_points.txt
unblockedGPT-1.4.1.dist-info/top_level.txt
unblockedGPT-1.4.1.dist-info/RECORD
