Metadata-Version: 2.1
Name: unblockedGPT
Version: 1.4.1
Summary: Placeholder
License-File: LICENSE
Requires-Dist: PyAutoGUI ==0.9.54
Requires-Dist: urllib3 ==1.26.15
Requires-Dist: requests
Requires-Dist: openai
Requires-Dist: streamlit
